{
  "protocol": "https://",
  "path": "metadata.opepen.art",
  "animation_url": "https://metadata.opepen.art/sets/031/?edition={EDITION}",
  "artist": "VV",
  "release": "031",
  "set": "Yearly Close",
  "names": {
    "1": "1x Listing",
    "4": "4x Listings",
    "5": "5x Listings",
    "10": "10x Listings",
    "20": "20x Listings",
    "40": "40x Listings"
  },
  "sets": {
    "1": [
      "{ID}/render"
    ],
    "4": [
      "{ID}/render",
      "{ID}/render",
      "{ID}/render",
      "{ID}/render"
    ],
    "5": [
      "{ID}/render",
      "{ID}/render",
      "{ID}/render",
      "{ID}/render",
      "{ID}/render"
    ],
    "10": [
      "{ID}/render",
      "{ID}/render",
      "{ID}/render",
      "{ID}/render",
      "{ID}/render",
      "{ID}/render",
      "{ID}/render",
      "{ID}/render",
      "{ID}/render",
      "{ID}/render"
    ],
    "20": [
      "{ID}/render",
      "{ID}/render",
      "{ID}/render",
      "{ID}/render",
      "{ID}/render",
      "{ID}/render",
      "{ID}/render",
      "{ID}/render",
      "{ID}/render",
      "{ID}/render",
      "{ID}/render",
      "{ID}/render",
      "{ID}/render",
      "{ID}/render",
      "{ID}/render",
      "{ID}/render",
      "{ID}/render",
      "{ID}/render",
      "{ID}/render",
      "{ID}/render"
    ],
    "40": [
      "{ID}/render",
      "{ID}/render",
      "{ID}/render",
      "{ID}/render",
      "{ID}/render",
      "{ID}/render",
      "{ID}/render",
      "{ID}/render",
      "{ID}/render",
      "{ID}/render",
      "{ID}/render",
      "{ID}/render",
      "{ID}/render",
      "{ID}/render",
      "{ID}/render",
      "{ID}/render",
      "{ID}/render",
      "{ID}/render",
      "{ID}/render",
      "{ID}/render",
      "{ID}/render",
      "{ID}/render",
      "{ID}/render",
      "{ID}/render",
      "{ID}/render",
      "{ID}/render",
      "{ID}/render",
      "{ID}/render",
      "{ID}/render",
      "{ID}/render",
      "{ID}/render",
      "{ID}/render",
      "{ID}/render",
      "{ID}/render",
      "{ID}/render",
      "{ID}/render",
      "{ID}/render",
      "{ID}/render",
      "{ID}/render",
      "{ID}/render"
    ]
  }
}
